{"name":"Search Successful","id":"search-jobs-on-the-page-elempleo;search-successful","testSteps":[{"number":1,"description":"Given I want to find jobs with a keyword","duration":19048,"startTime":"2019-03-04T15:34:24.562-05:00[America/Bogota]","screenshots":[{"screenshot":"39817c862c8d8837723117140a3704c449bd2e372099716e00ebe4e002a2c23e.png","timeStamp":1551731683609}],"result":"SUCCESS","precondition":false,"level":0,"children":[{"number":2,"description":"Openurl","duration":18458,"startTime":"2019-03-04T15:34:25.145-05:00[America/Bogota]","screenshots":[{"screenshot":"39817c862c8d8837723117140a3704c449bd2e372099716e00ebe4e002a2c23e.png","timeStamp":1551731683602}],"result":"SUCCESS","precondition":false,"level":1}]},{"number":3,"description":"When I search for jobs containing contador","duration":11947,"startTime":"2019-03-04T15:34:43.610-05:00[America/Bogota]","screenshots":[{"screenshot":"07aeb6b14b77ede664bacb453b77651fb6b347cadc1369ae2b0bc07f7bdce2e4.png","timeStamp":1551731695556}],"result":"SUCCESS","precondition":false,"level":0,"children":[{"number":4,"description":"Search: cont","duration":9590,"startTime":"2019-03-04T15:34:43.618-05:00[America/Bogota]","screenshots":[{"screenshot":"e0cba4af91f7d5680779e00b3536fba2b1ff71dae2af6f4c76bb27883473eee4.png","timeStamp":1551731693207}],"result":"SUCCESS","precondition":false,"level":1},{"number":5,"description":"Filters","duration":2344,"startTime":"2019-03-04T15:34:53.210-05:00[America/Bogota]","screenshots":[{"screenshot":"e0cba4af91f7d5680779e00b3536fba2b1ff71dae2af6f4c76bb27883473eee4.png","timeStamp":1551731693214},{"screenshot":"07aeb6b14b77ede664bacb453b77651fb6b347cadc1369ae2b0bc07f7bdce2e4.png","timeStamp":1551731695554}],"result":"SUCCESS","precondition":false,"level":1}]},{"number":6,"description":"Then I should only see items related to contador and save this in a .txt file","duration":5074,"startTime":"2019-03-04T15:34:55.557-05:00[America/Bogota]","screenshots":[{"screenshot":"4912dd3beb7454c341bc814181be68a3934e6b53e143ab035ec4410091fc0a47.png","timeStamp":1551731700631}],"result":"SUCCESS","precondition":false,"level":0,"children":[{"number":7,"description":"Read offerts","duration":3974,"startTime":"2019-03-04T15:34:55.560-05:00[America/Bogota]","screenshots":[{"screenshot":"4912dd3beb7454c341bc814181be68a3934e6b53e143ab035ec4410091fc0a47.png","timeStamp":1551731699534}],"result":"SUCCESS","precondition":false,"level":1},{"number":8,"description":"Screenshot","duration":651,"startTime":"2019-03-04T15:34:59.536-05:00[America/Bogota]","screenshots":[{"screenshot":"4912dd3beb7454c341bc814181be68a3934e6b53e143ab035ec4410091fc0a47.png","timeStamp":1551731699538},{"screenshot":"4912dd3beb7454c341bc814181be68a3934e6b53e143ab035ec4410091fc0a47.png","timeStamp":1551731700187}],"result":"SUCCESS","precondition":false,"level":1},{"number":9,"description":"Validate","duration":434,"startTime":"2019-03-04T15:35:00.189-05:00[America/Bogota]","screenshots":[{"screenshot":"4912dd3beb7454c341bc814181be68a3934e6b53e143ab035ec4410091fc0a47.png","timeStamp":1551731700191},{"screenshot":"4912dd3beb7454c341bc814181be68a3934e6b53e143ab035ec4410091fc0a47.png","timeStamp":1551731700622}],"result":"SUCCESS","precondition":false,"level":1}]}],"userStory":{"id":"search-jobs-on-the-page-elempleo","storyName":"Search jobs on the page elempleo","path":"src/test/resources/features/search.feature","narrative":"\t\tI want to find jobs whit any keyword","type":"feature"},"featureTag":{"name":"Features/Search jobs on the page elempleo","type":"feature"},"title":"Search Successful","tags":[{"name":"Search jobs on the page elempleo","type":"feature"}],"startTime":"2019-03-04T15:34:24.341-05:00[America/Bogota]","duration":36292,"projectKey":"","sessionId":"492a1f0de79137b6ae791d5bca384d91","driver":"chrome","manual":false,"testSource":"Cucumber","result":"SUCCESS"}